{
  "id": "BL-031",
  "title": "Campaign CRUD + Data Model",
  "priority": "Must Have",
  "effort": "M",
  "status": "Done",
  "sprint": "Backlog",
  "depends_on": [],
  "description": "Extend campaigns table with status, template config, generation config. New campaign_contacts junction table and campaign_templates table. CRUD API endpoints + CampaignsPage under Reach pillar. Foundation for message generation pipeline.",
  "theme": "Outreach Engine",
  "spec_file": "docs/specs/campaign-crud.md",
  "adr": "docs/adr/006-campaign-data-model.md",
  "created": "2026-02-23",
  "updated": "2026-02-23"
}