[
  {
    "name": "Sprint 1",
    "label": "S1",
    "sort_label": "CURRENT SPRINT",
    "description": "Playbook foundation: auto-save, phases, AI tone, chat markdown",
    "css_class": "sprint-1",
    "fill_class": "sprint-1-fill"
  },
  {
    "name": "Sprint 2",
    "label": "S2",
    "sort_label": "NEXT SPRINT",
    "description": "Chat persistence, agent architecture, transparent thinking, doc writing",
    "css_class": "sprint-2",
    "fill_class": "sprint-2-fill"
  },
  {
    "name": "Sprint 3",
    "label": "S3",
    "sort_label": "PLANNED SPRINT",
    "description": "Smart onboarding, templates, analyzers, contact management",
    "css_class": "sprint-3",
    "fill_class": "sprint-3-fill"
  },
  {
    "name": "Backlog",
    "label": "BL",
    "sort_label": "UNSCHEDULED",
    "description": "Future work \u2014 not yet scheduled",
    "css_class": "sprint-backlog",
    "fill_class": "sprint-backlog-fill"
  }
]